kos_protos/__init__.py
kos_protos/actuator_pb2.py
kos_protos/actuator_pb2.pyi
kos_protos/actuator_pb2_grpc.py
kos_protos/common_pb2.py
kos_protos/common_pb2.pyi
kos_protos/common_pb2_grpc.py
kos_protos/imu_pb2.py
kos_protos/imu_pb2.pyi
kos_protos/imu_pb2_grpc.py
kos_protos/inference_pb2.py
kos_protos/inference_pb2.pyi
kos_protos/inference_pb2_grpc.py
kos_protos/led_matrix_pb2.py
kos_protos/led_matrix_pb2.pyi
kos_protos/led_matrix_pb2_grpc.py
kos_protos/policy_pb2.py
kos_protos/policy_pb2.pyi
kos_protos/policy_pb2_grpc.py
kos_protos/process_manager_pb2.py
kos_protos/process_manager_pb2.pyi
kos_protos/process_manager_pb2_grpc.py
kos_protos/sim_pb2.py
kos_protos/sim_pb2.pyi
kos_protos/sim_pb2_grpc.py
kos_protos/sound_pb2.py
kos_protos/sound_pb2.pyi
kos_protos/sound_pb2_grpc.py
kos_protos/system_pb2.py
kos_protos/system_pb2.pyi
kos_protos/system_pb2_grpc.py
pykos/Cargo.toml
pykos/__init__.py
pykos/client.py
pykos/py.typed
pykos/services/__init__.py
pykos/services/actuator.py
pykos/services/imu.py
pykos/services/inference.py
pykos/services/led_matrix.py
pykos/services/policy.py
pykos/services/process_manager.py
pykos/services/sim.py
pykos/services/sound.py
pykos-0.7.10.dist-info/METADATA
pykos-0.7.10.dist-info/WHEEL
pykos-0.7.10.dist-info/entry_points.txt
pykos-0.7.10.dist-info/top_level.txt
pykos-0.7.10.dist-info/RECORD
