Metadata-Version: 2.4
Name: pykos
Version: 0.7.10
Summary: The KOS command line interface
Home-page: https://github.com/kscalelabs/kos
Author: pykos Contributors
Requires-Python: >=3.11
Requires-Dist: grpcio
Requires-Dist: protobuf>=5.29.0
Requires-Dist: googleapis-common-protos
Requires-Dist: nest-asyncio
Provides-Extra: dev
Requires-Dist: grpcio-tools; extra == "dev"
Requires-Dist: types-protobuf; extra == "dev"
Requires-Dist: black; extra == "dev"
Requires-Dist: darglint; extra == "dev"
Requires-Dist: mypy; extra == "dev"
Requires-Dist: mypy-protobuf; extra == "dev"
Requires-Dist: pytest; extra == "dev"
Requires-Dist: pytest-asyncio; extra == "dev"
Requires-Dist: ruff; extra == "dev"
Dynamic: author
Dynamic: description
Dynamic: description-content-type
Dynamic: home-page
Dynamic: provides-extra
Dynamic: requires-dist
Dynamic: requires-python
Dynamic: summary
